{
  "institution_unitid": "166939",
  "institution_name": "Mount Holyoke College",
  "institution_slug": "mount-holyoke-college-166939",
  "state": "ma",
  "cip_code": "1609",
  "cip_desc": "Romance Languages, Literatures, and Linguistics.",
  "credential_level": 3,
  "credential_desc": "Bachelor's Degree",
  "slug": "1609-c3",
  "earnings_median_4yr": null,
  "earnings_median_5yr": 54680,
  "earnings_count_4yr": null,
  "earnings_count_5yr": 4,
  "debt_median": 23828,
  "completers": 27,
  "completers_single_year": 36,
  "pooled_earnings": false,
  "history": {
    "earnings_median_4yr": [],
    "earnings_median_5yr": [
      {
        "year": 2019,
        "value": 54680.0
      }
    ],
    "debt_median": [
      {
        "year": 2014,
        "value": 19000.0
      },
      {
        "year": 2015,
        "value": 19000.0
      },
      {
        "year": 2016,
        "value": 19875.0
      },
      {
        "year": 2017,
        "value": 21000.0
      },
      {
        "year": 2018,
        "value": 23828.0
      }
    ],
    "completers": [
      {
        "year": 2014,
        "value": 24.0
      },
      {
        "year": 2015,
        "value": 18.0
      },
      {
        "year": 2016,
        "value": 30.0
      },
      {
        "year": 2017,
        "value": 27.0
      },
      {
        "year": 2018,
        "value": 36.0
      },
      {
        "year": 2019,
        "value": 27.0
      }
    ]
  },
  "long_arc": [
    {
      "metric": "debt_median",
      "from_year": 2014,
      "to_year": 2018,
      "from_value": 19000.0,
      "to_value": 23828.0,
      "pct_change": 0.2541052631578947,
      "direction": "rose"
    }
  ],
  "flags": [
    {
      "type": "long_arc_shift",
      "severity": "regression",
      "label": "Median program debt at exit",
      "summary": "Median program debt at exit at Romance Languages, Literatures, and Linguistics at Mount Holyoke College rose 25% between 2014 and 2018 ($19.0k → $23.8k).",
      "magnitude_pct": 25.4,
      "magnitude_abs": 4828.0,
      "baseline_year": 2014,
      "recent_year": 2018,
      "units": null,
      "history": [],
      "metric": "debt_median"
    }
  ],
  "institution": {
    "unitid": "166939",
    "slug": "mount-holyoke-college-166939",
    "name": "Mount Holyoke College",
    "city": "South Hadley",
    "city_slug": "south-hadley",
    "control": "private_nonprofit"
  },
  "peers_in_state": [
    {
      "institution_slug": "boston-college-164924",
      "institution_name": "Boston College",
      "earnings_median_5yr": 84188,
      "earnings_median_4yr": 74286,
      "debt_median": null,
      "completers": 9,
      "completers_single_year": 20,
      "pooled_earnings": false
    },
    {
      "institution_slug": "college-of-the-holy-cross-166124",
      "institution_name": "College of the Holy Cross",
      "earnings_median_5yr": 74806,
      "earnings_median_4yr": 64858,
      "debt_median": 26975,
      "completers": 21,
      "completers_single_year": 49,
      "pooled_earnings": false
    },
    {
      "institution_slug": "university-of-massachusetts-amherst-166629",
      "institution_name": "University of Massachusetts-Amherst",
      "earnings_median_5yr": 70508,
      "earnings_median_4yr": 61484,
      "debt_median": null,
      "completers": 91,
      "completers_single_year": 62,
      "pooled_earnings": false
    },
    {
      "institution_slug": "wellesley-college-168218",
      "institution_name": "Wellesley College",
      "earnings_median_5yr": 57010,
      "earnings_median_4yr": 44215,
      "debt_median": 10152,
      "completers": 26,
      "completers_single_year": 28,
      "pooled_earnings": false
    },
    {
      "institution_slug": "boston-university-164988",
      "institution_name": "Boston University",
      "earnings_median_5yr": 54222,
      "earnings_median_4yr": 57180,
      "debt_median": null,
      "completers": 10,
      "completers_single_year": 17,
      "pooled_earnings": false
    },
    {
      "institution_slug": "smith-college-167835",
      "institution_name": "Smith College",
      "earnings_median_5yr": 52652,
      "earnings_median_4yr": 43192,
      "debt_median": 19000,
      "completers": 33,
      "completers_single_year": 31,
      "pooled_earnings": false
    },
    {
      "institution_slug": "amherst-college-164465",
      "institution_name": "Amherst College",
      "earnings_median_5yr": null,
      "earnings_median_4yr": null,
      "debt_median": null,
      "completers": 21,
      "completers_single_year": 23,
      "pooled_earnings": false
    },
    {
      "institution_slug": "assumption-university-164562",
      "institution_name": "Assumption University",
      "earnings_median_5yr": null,
      "earnings_median_4yr": null,
      "debt_median": null,
      "completers": 7,
      "completers_single_year": 0,
      "pooled_earnings": false
    },
    {
      "institution_slug": "bentley-university-164739",
      "institution_name": "Bentley University",
      "earnings_median_5yr": null,
      "earnings_median_4yr": null,
      "debt_median": 26887,
      "completers": 0,
      "completers_single_year": 1,
      "pooled_earnings": false
    },
    {
      "institution_slug": "brandeis-university-165015",
      "institution_name": "Brandeis University",
      "earnings_median_5yr": null,
      "earnings_median_4yr": null,
      "debt_median": null,
      "completers": 1,
      "completers_single_year": null,
      "pooled_earnings": false
    },
    {
      "institution_slug": "bridgewater-state-university-165024",
      "institution_name": "Bridgewater State University",
      "earnings_median_5yr": null,
      "earnings_median_4yr": null,
      "debt_median": 28300,
      "completers": 4,
      "completers_single_year": 16,
      "pooled_earnings": false
    },
    {
      "institution_slug": "clark-university-165334",
      "institution_name": "Clark University",
      "earnings_median_5yr": null,
      "earnings_median_4yr": null,
      "debt_median": null,
      "completers": 17,
      "completers_single_year": 10,
      "pooled_earnings": false
    },
    {
      "institution_slug": "emmanuel-college-165671",
      "institution_name": "Emmanuel College",
      "earnings_median_5yr": null,
      "earnings_median_4yr": null,
      "debt_median": null,
      "completers": 2,
      "completers_single_year": 2,
      "pooled_earnings": false
    },
    {
      "institution_slug": "framingham-state-university-165866",
      "institution_name": "Framingham State University",
      "earnings_median_5yr": null,
      "earnings_median_4yr": null,
      "debt_median": null,
      "completers": 3,
      "completers_single_year": 4,
      "pooled_earnings": false
    },
    {
      "institution_slug": "gordon-college-165936",
      "institution_name": "Gordon College",
      "earnings_median_5yr": null,
      "earnings_median_4yr": null,
      "debt_median": null,
      "completers": 11,
      "completers_single_year": 8,
      "pooled_earnings": false
    },
    {
      "institution_slug": "harvard-university-166027",
      "institution_name": "Harvard University",
      "earnings_median_5yr": null,
      "earnings_median_4yr": null,
      "debt_median": null,
      "completers": 9,
      "completers_single_year": 4,
      "pooled_earnings": false
    },
    {
      "institution_slug": "lesley-university-166452",
      "institution_name": "Lesley University",
      "earnings_median_5yr": null,
      "earnings_median_4yr": null,
      "debt_median": null,
      "completers": 1,
      "completers_single_year": null,
      "pooled_earnings": false
    },
    {
      "institution_slug": "university-of-massachusetts-lowell-166513",
      "institution_name": "University of Massachusetts-Lowell",
      "earnings_median_5yr": null,
      "earnings_median_4yr": null,
      "debt_median": null,
      "completers": 0,
      "completers_single_year": 0,
      "pooled_earnings": false
    },
    {
      "institution_slug": "university-of-massachusetts-boston-166638",
      "institution_name": "University of Massachusetts-Boston",
      "earnings_median_5yr": null,
      "earnings_median_4yr": 48338,
      "debt_median": null,
      "completers": 13,
      "completers_single_year": 13,
      "pooled_earnings": false
    },
    {
      "institution_slug": "merrimack-college-166850",
      "institution_name": "Merrimack College",
      "earnings_median_5yr": null,
      "earnings_median_4yr": null,
      "debt_median": null,
      "completers": 3,
      "completers_single_year": 6,
      "pooled_earnings": false
    },
    {
      "institution_slug": "northeastern-university-167358",
      "institution_name": "Northeastern University",
      "earnings_median_5yr": null,
      "earnings_median_4yr": null,
      "debt_median": null,
      "completers": 2,
      "completers_single_year": 1,
      "pooled_earnings": false
    },
    {
      "institution_slug": "college-of-our-lady-of-the-elms-167394",
      "institution_name": "College of Our Lady of the Elms",
      "earnings_median_5yr": null,
      "earnings_median_4yr": null,
      "debt_median": null,
      "completers": 0,
      "completers_single_year": 1,
      "pooled_earnings": false
    },
    {
      "institution_slug": "salem-state-university-167729",
      "institution_name": "Salem State University",
      "earnings_median_5yr": null,
      "earnings_median_4yr": null,
      "debt_median": null,
      "completers": 12,
      "completers_single_year": 19,
      "pooled_earnings": false
    },
    {
      "institution_slug": "simmons-university-167783",
      "institution_name": "Simmons University",
      "earnings_median_5yr": null,
      "earnings_median_4yr": null,
      "debt_median": null,
      "completers": 3,
      "completers_single_year": 3,
      "pooled_earnings": false
    },
    {
      "institution_slug": "university-of-massachusetts-dartmouth-167987",
      "institution_name": "University of Massachusetts-Dartmouth",
      "earnings_median_5yr": null,
      "earnings_median_4yr": null,
      "debt_median": null,
      "completers": 3,
      "completers_single_year": 6,
      "pooled_earnings": false
    },
    {
      "institution_slug": "stonehill-college-167996",
      "institution_name": "Stonehill College",
      "earnings_median_5yr": null,
      "earnings_median_4yr": null,
      "debt_median": null,
      "completers": 4,
      "completers_single_year": 9,
      "pooled_earnings": false
    },
    {
      "institution_slug": "suffolk-university-168005",
      "institution_name": "Suffolk University",
      "earnings_median_5yr": null,
      "earnings_median_4yr": null,
      "debt_median": null,
      "completers": 1,
      "completers_single_year": 7,
      "pooled_earnings": false
    },
    {
      "institution_slug": "tufts-university-168148",
      "institution_name": "Tufts University",
      "earnings_median_5yr": null,
      "earnings_median_4yr": null,
      "debt_median": 15200,
      "completers": 52,
      "completers_single_year": 56,
      "pooled_earnings": false
    },
    {
      "institution_slug": "westfield-state-university-168263",
      "institution_name": "Westfield State University",
      "earnings_median_5yr": null,
      "earnings_median_4yr": null,
      "debt_median": 27000,
      "completers": 5,
      "completers_single_year": 6,
      "pooled_earnings": false
    },
    {
      "institution_slug": "wheaton-college-massachusetts-168281",
      "institution_name": "Wheaton College (Massachusetts)",
      "earnings_median_5yr": null,
      "earnings_median_4yr": null,
      "debt_median": null,
      "completers": 0,
      "completers_single_year": 0,
      "pooled_earnings": false
    },
    {
      "institution_slug": "williams-college-168342",
      "institution_name": "Williams College",
      "earnings_median_5yr": null,
      "earnings_median_4yr": null,
      "debt_median": null,
      "completers": 17,
      "completers_single_year": 26,
      "pooled_earnings": false
    },
    {
      "institution_slug": "worcester-state-university-168430",
      "institution_name": "Worcester State University",
      "earnings_median_5yr": null,
      "earnings_median_4yr": null,
      "debt_median": null,
      "completers": 6,
      "completers_single_year": 11,
      "pooled_earnings": false
    }
  ],
  "roi": {
    "suppressed": false,
    "n_obs": 4,
    "inputs": {
      "years_to_complete": 4,
      "cost_per_year_default": 21565,
      "cost_total_default": 86260,
      "cost_source": "NPT43_PRIV",
      "income_bracket_default": "48_75k",
      "earnings_at_completion": 54680,
      "earnings_anchor_year": 5,
      "debt_median": 23828,
      "cip_family": "16",
      "hs_baseline_state": 42600
    },
    "default_assumptions": {
      "discount_rate": 0.05,
      "horizon_years": 40,
      "selection_adjusted": false
    },
    "default_result": {
      "npv": 159409,
      "breakeven_year": 20
    }
  },
  "source": {
    "name": "College Scorecard + IPEDS HD",
    "vintage": "2025-05",
    "retrieved": "2026-05-08",
    "history_vintages": [
      1996,
      1997,
      1998,
      1999,
      2000,
      2001,
      2002,
      2003,
      2004,
      2005,
      2006,
      2007,
      2008,
      2009,
      2010,
      2011,
      2012,
      2013,
      2014,
      2015,
      2016,
      2017,
      2018,
      2019,
      2020,
      2021,
      2022,
      2023,
      2024
    ]
  }
}