{
  "institution": {
    "unitid": "489256",
    "opeid6": "042668",
    "name": "Caribbean Aviation Training Institute Inc",
    "slug": "caribbean-aviation-training-institute-inc-489256",
    "state": "pr",
    "city": "Carolina",
    "city_slug": "carolina",
    "zip5": "00979",
    "address": "Ave. Jose A. Santana, Ed. World Cargo, 2nd Floor Base Muniz",
    "latitude": 18.439873,
    "longitude": -65.997043,
    "control": "private_forprofit",
    "pred_degree": "certificate",
    "highest_degree": "certificate",
    "main_campus": true,
    "locale": "21",
    "carnegie_basic": -2,
    "sector_code": 9,
    "hbcu": false,
    "tribal": false,
    "earnings_median_4yr": null,
    "earnings_median_5yr": null,
    "earnings_median_6yr": null,
    "earnings_median_8yr": null,
    "earnings_median_10yr": null,
    "completion_rate_150": 0.9709,
    "completion_rate_100": 0.9709,
    "retention_rate": 0.9897,
    "admission_rate": null,
    "enrollment_undergrad": 191,
    "enrollment_total": null,
    "cost_attendance": 15487,
    "tuition_in_state": 15480,
    "tuition_out_of_state": 15480,
    "avg_net_price_pub": null,
    "avg_net_price_priv": 10911,
    "cost_by_income": {
      "0_30k": 10911,
      "30_48k": null,
      "48_75k": null,
      "75_110k": null,
      "110k_plus": null,
      "sticker": 15487,
      "sector": "priv"
    },
    "median_debt": null,
    "default_rate": null,
    "pell_share": 0.615,
    "history": {
      "completion_rate_150": [],
      "completion_rate_100": [],
      "retention_rate": [
        {
          "year": 2017,
          "value": 0.9807
        },
        {
          "year": 2018,
          "value": 0.9657
        },
        {
          "year": 2019,
          "value": 0.9657
        },
        {
          "year": 2020,
          "value": 0.9853
        },
        {
          "year": 2021,
          "value": 0.9854
        },
        {
          "year": 2022,
          "value": 0.9854
        },
        {
          "year": 2023,
          "value": 0.9897
        },
        {
          "year": 2024,
          "value": 0.9839
        }
      ],
      "admission_rate": [],
      "enrollment_undergrad": [],
      "tuition_in_state": [
        {
          "year": 2017,
          "value": 11065.0
        },
        {
          "year": 2018,
          "value": 11065.0
        },
        {
          "year": 2019,
          "value": 11065.0
        },
        {
          "year": 2020,
          "value": 11065.0
        },
        {
          "year": 2021,
          "value": 11065.0
        },
        {
          "year": 2022,
          "value": 12780.0
        },
        {
          "year": 2023,
          "value": 15480.0
        },
        {
          "year": 2024,
          "value": 15480.0
        }
      ],
      "tuition_out_of_state": [
        {
          "year": 2017,
          "value": 11065.0
        },
        {
          "year": 2018,
          "value": 11065.0
        },
        {
          "year": 2019,
          "value": 11065.0
        },
        {
          "year": 2020,
          "value": 11065.0
        },
        {
          "year": 2021,
          "value": 11065.0
        },
        {
          "year": 2022,
          "value": 12780.0
        },
        {
          "year": 2023,
          "value": 15480.0
        },
        {
          "year": 2024,
          "value": 15480.0
        }
      ],
      "cost_attendance": [
        {
          "year": 2018,
          "value": 13588.0
        },
        {
          "year": 2019,
          "value": 13629.0
        },
        {
          "year": 2020,
          "value": 13827.0
        },
        {
          "year": 2021,
          "value": 13803.0
        },
        {
          "year": 2022,
          "value": 13803.0
        },
        {
          "year": 2023,
          "value": 15487.0
        },
        {
          "year": 2024,
          "value": 18210.0
        }
      ],
      "avg_net_price_pub": [],
      "avg_net_price_priv": [
        {
          "year": 2018,
          "value": 9544.0
        },
        {
          "year": 2019,
          "value": 8973.0
        },
        {
          "year": 2020,
          "value": 8566.0
        },
        {
          "year": 2021,
          "value": 8546.0
        },
        {
          "year": 2022,
          "value": 8546.0
        },
        {
          "year": 2023,
          "value": 10911.0
        },
        {
          "year": 2024,
          "value": 12379.0
        }
      ],
      "median_debt": [],
      "default_rate": [],
      "pell_share": [
        {
          "year": 2017,
          "value": 0.0
        },
        {
          "year": 2018,
          "value": 0.491
        },
        {
          "year": 2019,
          "value": 0.527
        },
        {
          "year": 2020,
          "value": 0.5856
        },
        {
          "year": 2021,
          "value": 0.5991
        },
        {
          "year": 2022,
          "value": 0.5991
        },
        {
          "year": 2023,
          "value": 0.615
        },
        {
          "year": 2024,
          "value": 0.6021
        }
      ],
      "earnings_median_6yr": [],
      "earnings_median_8yr": [],
      "earnings_median_10yr": []
    },
    "long_arc": [
      {
        "metric": "tuition_in_state",
        "from_year": 2017,
        "to_year": 2024,
        "from_value": 11065.0,
        "to_value": 15480.0,
        "pct_change": 0.39900587437867147,
        "direction": "rose"
      },
      {
        "metric": "tuition_out_of_state",
        "from_year": 2017,
        "to_year": 2024,
        "from_value": 11065.0,
        "to_value": 15480.0,
        "pct_change": 0.39900587437867147,
        "direction": "rose"
      },
      {
        "metric": "pell_share",
        "from_year": 2017,
        "to_year": 2024,
        "from_value": 0.0,
        "to_value": 0.6021,
        "pct_change": 12.041999999999998,
        "direction": "rose"
      }
    ],
    "flags": [
      {
        "type": "long_arc_shift",
        "severity": "regression",
        "label": "In-state tuition",
        "summary": "In-state tuition at Caribbean Aviation Training Institute Inc rose 40% between 2021 and 2024 ($11.1k → $15.5k).",
        "magnitude_pct": 39.9,
        "magnitude_abs": 4415.0,
        "baseline_year": 2021,
        "recent_year": 2024,
        "units": null,
        "history": [],
        "metric": "tuition_in_state"
      },
      {
        "type": "long_arc_shift",
        "severity": "regression",
        "label": "Out-of-state tuition",
        "summary": "Out-of-state tuition at Caribbean Aviation Training Institute Inc rose 40% between 2021 and 2024 ($11.1k → $15.5k).",
        "magnitude_pct": 39.9,
        "magnitude_abs": 4415.0,
        "baseline_year": 2021,
        "recent_year": 2024,
        "units": null,
        "history": [],
        "metric": "tuition_out_of_state"
      }
    ]
  },
  "programs_by_family": {
    "47": [
      {
        "slug": "4706-c1",
        "cip_code": "4706",
        "cip_desc": "Vehicle Maintenance and Repair Technologies.",
        "credential_level": 1,
        "credential_desc": "Undergraduate Certificate or Diploma",
        "earnings_median_5yr": null,
        "earnings_median_4yr": null,
        "earnings_history_5yr": [],
        "earnings_history_4yr": [],
        "debt_median": null,
        "debt_history": [],
        "completers": 74,
        "completers_single_year": 74,
        "completers_history": [
          {
            "year": 2015,
            "value": 41.0
          },
          {
            "year": 2016,
            "value": 69.0
          },
          {
            "year": 2017,
            "value": 69.0
          },
          {
            "year": 2018,
            "value": 74.0
          },
          {
            "year": 2019,
            "value": 74.0
          }
        ],
        "long_arc": []
      }
    ]
  },
  "programs": [
    {
      "slug": "4706-c1",
      "cip_code": "4706",
      "cip_desc": "Vehicle Maintenance and Repair Technologies.",
      "credential_level": 1,
      "credential_desc": "Undergraduate Certificate or Diploma",
      "earnings_median_5yr": null,
      "earnings_median_4yr": null,
      "earnings_history_5yr": [],
      "earnings_history_4yr": [],
      "debt_median": null,
      "debt_history": [],
      "completers": 74,
      "completers_single_year": 74,
      "completers_history": [
        {
          "year": 2015,
          "value": 41.0
        },
        {
          "year": 2016,
          "value": 69.0
        },
        {
          "year": 2017,
          "value": 69.0
        },
        {
          "year": 2018,
          "value": 74.0
        },
        {
          "year": 2019,
          "value": 74.0
        }
      ],
      "long_arc": []
    }
  ],
  "program_count": 1,
  "similar": [
    {
      "slug": "liceo-de-arte-dise-o-y-comercio-376330",
      "name": "Liceo de Arte-Dise-O y Comercio",
      "city": "Caguas",
      "control": "private_forprofit",
      "pred_degree": "certificate",
      "earnings_median_10yr": 15501,
      "completion_rate_150": 0.7222,
      "enrollment_undergrad": 190
    },
    {
      "slug": "ppg-technical-college-486576",
      "name": "PPG Technical College",
      "city": "Caguas",
      "control": "private_forprofit",
      "pred_degree": "certificate",
      "earnings_median_10yr": null,
      "completion_rate_150": 0.5429,
      "enrollment_undergrad": 194
    },
    {
      "slug": "professional-technical-institution-409193",
      "name": "Professional Technical Institution",
      "city": "Bayamon",
      "control": "private_forprofit",
      "pred_degree": "certificate",
      "earnings_median_10yr": 24336,
      "completion_rate_150": 0.8696,
      "enrollment_undergrad": 187
    },
    {
      "slug": "escuela-tecnica-de-electricidad-431123",
      "name": "Escuela Tecnica de Electricidad",
      "city": "Ponce",
      "control": "private_forprofit",
      "pred_degree": "certificate",
      "earnings_median_10yr": 26398,
      "completion_rate_150": 0.9091,
      "enrollment_undergrad": 195
    },
    {
      "slug": "academia-serrant-inc-421896",
      "name": "Academia Serrant Inc",
      "city": "Ponce",
      "control": "private_forprofit",
      "pred_degree": "certificate",
      "earnings_median_10yr": 18422,
      "completion_rate_150": 0.8678,
      "enrollment_undergrad": 186
    }
  ],
  "roi": {
    "default_program_slug": null,
    "programs_available": [
      {
        "slug": "4706-c1",
        "label": "Vehicle Maintenance and Repair Technologies · Undergraduate Certificate or Diploma",
        "cip_family": "47",
        "completers": 74,
        "has_earnings": false,
        "earnings_at_completion": null,
        "earnings_anchor_year": 4,
        "debt_median": null,
        "years_to_complete": 1,
        "default_result": null
      }
    ]
  },
  "source": {
    "name": "College Scorecard + IPEDS HD",
    "vintage": "2025-05",
    "retrieved": "2026-05-08",
    "history_vintages": [
      1996,
      1997,
      1998,
      1999,
      2000,
      2001,
      2002,
      2003,
      2004,
      2005,
      2006,
      2007,
      2008,
      2009,
      2010,
      2011,
      2012,
      2013,
      2014,
      2015,
      2016,
      2017,
      2018,
      2019,
      2020,
      2021,
      2022,
      2023,
      2024
    ]
  }
}