{
  "state": "wv",
  "name": "Charleston",
  "slug": "charleston",
  "institution_count": 4,
  "institutions": [
    {
      "unitid": "430795",
      "slug": "carver-career-center-430795",
      "name": "Carver Career Center",
      "city": "Charleston",
      "city_slug": "charleston",
      "control": "public",
      "pred_degree": "certificate",
      "earnings_median_5yr": null,
      "earnings_median_10yr": 33739,
      "earnings_progression": [
        {
          "year": 4,
          "value": null
        },
        {
          "year": 5,
          "value": null
        },
        {
          "year": 6,
          "value": 28840
        },
        {
          "year": 8,
          "value": 31919
        },
        {
          "year": 10,
          "value": 33739
        }
      ],
      "completion_rate_150": 0.8431,
      "completion_rate_history": [
        {
          "year": 1998,
          "value": 0.7391
        },
        {
          "year": 1999,
          "value": 0.7381
        },
        {
          "year": 2000,
          "value": 0.7051
        },
        {
          "year": 2002,
          "value": 0.2133
        },
        {
          "year": 2003,
          "value": 1.0
        },
        {
          "year": 2004,
          "value": 0.3626
        },
        {
          "year": 2005,
          "value": 0.8556
        },
        {
          "year": 2006,
          "value": 0.7561
        },
        {
          "year": 2007,
          "value": 0.6909
        },
        {
          "year": 2008,
          "value": 0.7377
        },
        {
          "year": 2009,
          "value": 1.0
        }
      ],
      "enrollment_undergrad": 163,
      "enrollment_history": [
        {
          "year": 1997,
          "value": 0.0
        },
        {
          "year": 1998,
          "value": 151.0
        },
        {
          "year": 1999,
          "value": 204.0
        },
        {
          "year": 2001,
          "value": 193.0
        },
        {
          "year": 2002,
          "value": 347.0
        },
        {
          "year": 2003,
          "value": 302.0
        },
        {
          "year": 2004,
          "value": 306.0
        },
        {
          "year": 2005,
          "value": 212.0
        },
        {
          "year": 2006,
          "value": 224.0
        },
        {
          "year": 2007,
          "value": 222.0
        },
        {
          "year": 2008,
          "value": 200.0
        },
        {
          "year": 2009,
          "value": 267.0
        },
        {
          "year": 2010,
          "value": 217.0
        },
        {
          "year": 2011,
          "value": 264.0
        },
        {
          "year": 2012,
          "value": 183.0
        },
        {
          "year": 2013,
          "value": 276.0
        },
        {
          "year": 2014,
          "value": 259.0
        },
        {
          "year": 2015,
          "value": 223.0
        },
        {
          "year": 2016,
          "value": 241.0
        },
        {
          "year": 2017,
          "value": 246.0
        },
        {
          "year": 2018,
          "value": 170.0
        },
        {
          "year": 2019,
          "value": 177.0
        },
        {
          "year": 2020,
          "value": 178.0
        },
        {
          "year": 2021,
          "value": 155.0
        },
        {
          "year": 2022,
          "value": 155.0
        },
        {
          "year": 2023,
          "value": 163.0
        },
        {
          "year": 2024,
          "value": 169.0
        }
      ],
      "median_debt": null,
      "default_rate": null,
      "tuition_in_state": null,
      "tuition_out_of_state": null,
      "long_arc": [
        {
          "metric": "completion_rate_150",
          "from_year": 1998,
          "to_year": 2009,
          "from_value": 0.7391,
          "to_value": 1.0,
          "pct_change": 0.3529968881071574,
          "direction": "rose"
        },
        {
          "metric": "retention_rate",
          "from_year": 2004,
          "to_year": 2024,
          "from_value": 0.81,
          "to_value": 0.9143,
          "pct_change": 0.12876543209876537,
          "direction": "rose"
        },
        {
          "metric": "enrollment_undergrad",
          "from_year": 1997,
          "to_year": 2024,
          "from_value": 0.0,
          "to_value": 169.0,
          "pct_change": 0.845,
          "direction": "rose"
        },
        {
          "metric": "pell_share",
          "from_year": 2008,
          "to_year": 2024,
          "from_value": 0.5316,
          "to_value": 0.7358,
          "pct_change": 0.38412340105342374,
          "direction": "rose"
        },
        {
          "metric": "earnings_median_10yr",
          "from_year": 2009,
          "to_year": 2020,
          "from_value": 27900.0,
          "to_value": 33739.0,
          "pct_change": 0.2092831541218638,
          "direction": "rose"
        },
        {
          "metric": "earnings_median_8yr",
          "from_year": 2007,
          "to_year": 2020,
          "from_value": 24800.0,
          "to_value": 31919.0,
          "pct_change": 0.2870564516129032,
          "direction": "rose"
        },
        {
          "metric": "earnings_median_6yr",
          "from_year": 2005,
          "to_year": 2020,
          "from_value": 22800.0,
          "to_value": 28840.0,
          "pct_change": 0.2649122807017544,
          "direction": "rose"
        }
      ]
    },
    {
      "unitid": "237303",
      "slug": "charleston-school-of-beauty-culture-237303",
      "name": "Charleston School of Beauty Culture",
      "city": "Charleston",
      "city_slug": "charleston",
      "control": "private_forprofit",
      "pred_degree": "certificate",
      "earnings_median_5yr": null,
      "earnings_median_10yr": 17827,
      "earnings_progression": [
        {
          "year": 4,
          "value": null
        },
        {
          "year": 5,
          "value": null
        },
        {
          "year": 6,
          "value": 17000
        },
        {
          "year": 8,
          "value": 19929
        },
        {
          "year": 10,
          "value": 17827
        }
      ],
      "completion_rate_150": 0.5,
      "completion_rate_history": [
        {
          "year": 1997,
          "value": 0.5082
        },
        {
          "year": 1999,
          "value": 0.4828
        },
        {
          "year": 2001,
          "value": 0.7241
        },
        {
          "year": 2002,
          "value": 0.6721
        },
        {
          "year": 2003,
          "value": 0.4894
        },
        {
          "year": 2004,
          "value": 0.4355
        },
        {
          "year": 2005,
          "value": 0.3148
        },
        {
          "year": 2006,
          "value": 0.8727
        },
        {
          "year": 2007,
          "value": 0.5778
        },
        {
          "year": 2008,
          "value": 0.4265
        },
        {
          "year": 2009,
          "value": 0.4032
        }
      ],
      "enrollment_undergrad": 54,
      "enrollment_history": [
        {
          "year": 1996,
          "value": 89.0
        },
        {
          "year": 1997,
          "value": 73.0
        },
        {
          "year": 1998,
          "value": 70.0
        },
        {
          "year": 1999,
          "value": 67.0
        },
        {
          "year": 2001,
          "value": 54.0
        },
        {
          "year": 2002,
          "value": 88.0
        },
        {
          "year": 2003,
          "value": 66.0
        },
        {
          "year": 2004,
          "value": 80.0
        },
        {
          "year": 2005,
          "value": 77.0
        },
        {
          "year": 2006,
          "value": 110.0
        },
        {
          "year": 2007,
          "value": 85.0
        },
        {
          "year": 2008,
          "value": 80.0
        },
        {
          "year": 2009,
          "value": 108.0
        },
        {
          "year": 2010,
          "value": 100.0
        },
        {
          "year": 2011,
          "value": 108.0
        },
        {
          "year": 2012,
          "value": 104.0
        },
        {
          "year": 2013,
          "value": 121.0
        },
        {
          "year": 2014,
          "value": 121.0
        },
        {
          "year": 2015,
          "value": 104.0
        },
        {
          "year": 2016,
          "value": 75.0
        },
        {
          "year": 2017,
          "value": 83.0
        },
        {
          "year": 2018,
          "value": 80.0
        },
        {
          "year": 2019,
          "value": 87.0
        },
        {
          "year": 2020,
          "value": 62.0
        },
        {
          "year": 2021,
          "value": 52.0
        },
        {
          "year": 2022,
          "value": 55.0
        },
        {
          "year": 2023,
          "value": 54.0
        },
        {
          "year": 2024,
          "value": 46.0
        }
      ],
      "median_debt": 5500,
      "default_rate": 0.0,
      "tuition_in_state": null,
      "tuition_out_of_state": null,
      "long_arc": [
        {
          "metric": "completion_rate_150",
          "from_year": 1997,
          "to_year": 2009,
          "from_value": 0.5082,
          "to_value": 0.4032,
          "pct_change": -0.20661157024793386,
          "direction": "fell"
        },
        {
          "metric": "retention_rate",
          "from_year": 2004,
          "to_year": 2024,
          "from_value": 0.6,
          "to_value": 0.7037,
          "pct_change": 0.17283333333333337,
          "direction": "rose"
        },
        {
          "metric": "enrollment_undergrad",
          "from_year": 1996,
          "to_year": 2024,
          "from_value": 89.0,
          "to_value": 46.0,
          "pct_change": -0.215,
          "direction": "fell"
        },
        {
          "metric": "median_debt",
          "from_year": 1997,
          "to_year": 2020,
          "from_value": 2625.0,
          "to_value": 6128.0,
          "pct_change": 1.3344761904761904,
          "direction": "rose"
        },
        {
          "metric": "default_rate",
          "from_year": 2011,
          "to_year": 2024,
          "from_value": 0.34,
          "to_value": 0.0,
          "pct_change": -1.0,
          "direction": "fell"
        },
        {
          "metric": "earnings_median_8yr",
          "from_year": 2005,
          "to_year": 2020,
          "from_value": 13500.0,
          "to_value": 19929.0,
          "pct_change": 0.4286,
          "direction": "rose"
        },
        {
          "metric": "earnings_median_6yr",
          "from_year": 2003,
          "to_year": 2020,
          "from_value": 12400.0,
          "to_value": 17000.0,
          "pct_change": 0.30666666666666664,
          "direction": "rose"
        }
      ]
    },
    {
      "unitid": "448275",
      "slug": "mountain-state-school-of-massage-448275",
      "name": "Mountain State School of Massage",
      "city": "Charleston",
      "city_slug": "charleston",
      "control": "private_forprofit",
      "pred_degree": "certificate",
      "earnings_median_5yr": null,
      "earnings_median_10yr": 27545,
      "earnings_progression": [
        {
          "year": 4,
          "value": null
        },
        {
          "year": 5,
          "value": null
        },
        {
          "year": 6,
          "value": null
        },
        {
          "year": 8,
          "value": 26784
        },
        {
          "year": 10,
          "value": 27545
        }
      ],
      "completion_rate_150": 0.7826,
      "completion_rate_history": [
        {
          "year": 2006,
          "value": 0.8776
        },
        {
          "year": 2007,
          "value": 0.8095
        },
        {
          "year": 2008,
          "value": 0.8095
        },
        {
          "year": 2009,
          "value": 0.7059
        }
      ],
      "enrollment_undergrad": 33,
      "enrollment_history": [
        {
          "year": 2006,
          "value": 43.0
        },
        {
          "year": 2007,
          "value": 49.0
        },
        {
          "year": 2008,
          "value": 52.0
        },
        {
          "year": 2009,
          "value": 41.0
        },
        {
          "year": 2010,
          "value": 24.0
        },
        {
          "year": 2011,
          "value": 33.0
        },
        {
          "year": 2012,
          "value": 26.0
        },
        {
          "year": 2013,
          "value": 21.0
        },
        {
          "year": 2014,
          "value": 26.0
        },
        {
          "year": 2015,
          "value": 37.0
        },
        {
          "year": 2016,
          "value": 15.0
        },
        {
          "year": 2017,
          "value": 30.0
        },
        {
          "year": 2018,
          "value": 18.0
        },
        {
          "year": 2019,
          "value": 30.0
        },
        {
          "year": 2020,
          "value": 24.0
        },
        {
          "year": 2021,
          "value": 24.0
        },
        {
          "year": 2022,
          "value": 19.0
        },
        {
          "year": 2023,
          "value": 33.0
        },
        {
          "year": 2024,
          "value": 32.0
        }
      ],
      "median_debt": 8181,
      "default_rate": 0.0,
      "tuition_in_state": null,
      "tuition_out_of_state": null,
      "long_arc": [
        {
          "metric": "median_debt",
          "from_year": 2006,
          "to_year": 2019,
          "from_value": 5394.0,
          "to_value": 8181.0,
          "pct_change": 0.5166852057842046,
          "direction": "rose"
        },
        {
          "metric": "default_rate",
          "from_year": 2011,
          "to_year": 2024,
          "from_value": 0.314,
          "to_value": 0.0,
          "pct_change": -1.0,
          "direction": "fell"
        },
        {
          "metric": "pell_share",
          "from_year": 2008,
          "to_year": 2024,
          "from_value": 0.5373,
          "to_value": 0.9091,
          "pct_change": 0.6919784105713754,
          "direction": "rose"
        }
      ]
    },
    {
      "unitid": "237312",
      "slug": "university-of-charleston-237312",
      "name": "University of Charleston",
      "city": "Charleston",
      "city_slug": "charleston",
      "control": "private_nonprofit",
      "pred_degree": "bachelors",
      "earnings_median_5yr": null,
      "earnings_median_10yr": 55774,
      "earnings_progression": [
        {
          "year": 4,
          "value": null
        },
        {
          "year": 5,
          "value": null
        },
        {
          "year": 6,
          "value": 42698
        },
        {
          "year": 8,
          "value": 49711
        },
        {
          "year": 10,
          "value": 55774
        }
      ],
      "completion_rate_150": 0.4633,
      "completion_rate_history": [
        {
          "year": 1997,
          "value": 0.5222
        },
        {
          "year": 1998,
          "value": 0.4383
        },
        {
          "year": 1999,
          "value": 0.4239
        },
        {
          "year": 2000,
          "value": 0.5829
        },
        {
          "year": 2001,
          "value": 0.4918
        },
        {
          "year": 2002,
          "value": 0.4305
        },
        {
          "year": 2003,
          "value": 0.4695
        },
        {
          "year": 2004,
          "value": 0.4097
        },
        {
          "year": 2005,
          "value": 0.5054
        },
        {
          "year": 2006,
          "value": 0.4241
        },
        {
          "year": 2007,
          "value": 0.4321
        },
        {
          "year": 2008,
          "value": 0.4565
        },
        {
          "year": 2009,
          "value": 0.4478
        },
        {
          "year": 2010,
          "value": 0.414
        },
        {
          "year": 2011,
          "value": 0.5199
        },
        {
          "year": 2012,
          "value": 0.4172
        },
        {
          "year": 2013,
          "value": 0.4568
        },
        {
          "year": 2014,
          "value": 0.3505
        },
        {
          "year": 2015,
          "value": 0.4689
        },
        {
          "year": 2016,
          "value": 0.397
        },
        {
          "year": 2017,
          "value": 0.4939
        },
        {
          "year": 2018,
          "value": 0.4667
        },
        {
          "year": 2019,
          "value": 0.3838
        },
        {
          "year": 2020,
          "value": 0.4639
        },
        {
          "year": 2021,
          "value": 0.4304
        },
        {
          "year": 2022,
          "value": 0.4175
        },
        {
          "year": 2023,
          "value": 0.4633
        },
        {
          "year": 2024,
          "value": 0.4555
        }
      ],
      "enrollment_undergrad": 2083,
      "enrollment_history": [
        {
          "year": 1996,
          "value": 1376.0
        },
        {
          "year": 1997,
          "value": 1364.0
        },
        {
          "year": 1998,
          "value": 1285.0
        },
        {
          "year": 1999,
          "value": 1162.0
        },
        {
          "year": 2001,
          "value": 1021.0
        },
        {
          "year": 2002,
          "value": 936.0
        },
        {
          "year": 2003,
          "value": 931.0
        },
        {
          "year": 2004,
          "value": 835.0
        },
        {
          "year": 2005,
          "value": 900.0
        },
        {
          "year": 2006,
          "value": 1065.0
        },
        {
          "year": 2007,
          "value": 1170.0
        },
        {
          "year": 2008,
          "value": 1120.0
        },
        {
          "year": 2009,
          "value": 1006.0
        },
        {
          "year": 2010,
          "value": 1119.0
        },
        {
          "year": 2011,
          "value": 999.0
        },
        {
          "year": 2012,
          "value": 1016.0
        },
        {
          "year": 2013,
          "value": 1373.0
        },
        {
          "year": 2014,
          "value": 1513.0
        },
        {
          "year": 2015,
          "value": 1706.0
        },
        {
          "year": 2016,
          "value": 1733.0
        },
        {
          "year": 2017,
          "value": 1810.0
        },
        {
          "year": 2018,
          "value": 1910.0
        },
        {
          "year": 2019,
          "value": 1893.0
        },
        {
          "year": 2020,
          "value": 2075.0
        },
        {
          "year": 2021,
          "value": 2118.0
        },
        {
          "year": 2022,
          "value": 2330.0
        },
        {
          "year": 2023,
          "value": 2083.0
        },
        {
          "year": 2024,
          "value": 2259.0
        }
      ],
      "median_debt": 12666,
      "default_rate": 0.0,
      "tuition_in_state": 32842,
      "tuition_out_of_state": 32842,
      "long_arc": [
        {
          "metric": "retention_rate",
          "from_year": 2004,
          "to_year": 2024,
          "from_value": 0.64,
          "to_value": 0.7479,
          "pct_change": 0.16859375,
          "direction": "rose"
        },
        {
          "metric": "enrollment_undergrad",
          "from_year": 1996,
          "to_year": 2024,
          "from_value": 1376.0,
          "to_value": 2259.0,
          "pct_change": 0.6417151162790697,
          "direction": "rose"
        },
        {
          "metric": "tuition_in_state",
          "from_year": 2001,
          "to_year": 2024,
          "from_value": 14900.0,
          "to_value": 33800.0,
          "pct_change": 1.2684563758389262,
          "direction": "rose"
        },
        {
          "metric": "tuition_out_of_state",
          "from_year": 2001,
          "to_year": 2024,
          "from_value": 14900.0,
          "to_value": 33800.0,
          "pct_change": 1.2684563758389262,
          "direction": "rose"
        },
        {
          "metric": "median_debt",
          "from_year": 1997,
          "to_year": 2020,
          "from_value": 7975.0,
          "to_value": 19500.0,
          "pct_change": 1.445141065830721,
          "direction": "rose"
        },
        {
          "metric": "default_rate",
          "from_year": 2011,
          "to_year": 2024,
          "from_value": 0.141,
          "to_value": 0.0,
          "pct_change": -1.0,
          "direction": "fell"
        },
        {
          "metric": "earnings_median_10yr",
          "from_year": 2007,
          "to_year": 2020,
          "from_value": 40700.0,
          "to_value": 55774.0,
          "pct_change": 0.3703685503685504,
          "direction": "rose"
        },
        {
          "metric": "earnings_median_8yr",
          "from_year": 2005,
          "to_year": 2020,
          "from_value": 37900.0,
          "to_value": 49711.0,
          "pct_change": 0.3116358839050132,
          "direction": "rose"
        },
        {
          "metric": "earnings_median_6yr",
          "from_year": 2003,
          "to_year": 2020,
          "from_value": 34200.0,
          "to_value": 42698.0,
          "pct_change": 0.2484795321637427,
          "direction": "rose"
        }
      ]
    }
  ],
  "earnings_median_city": 30642,
  "completion_rate_city": 0.6413,
  "completion_history_city": [
    {
      "year": 1997,
      "value": 0.5152
    },
    {
      "year": 1998,
      "value": 0.5887
    },
    {
      "year": 1999,
      "value": 0.4828
    },
    {
      "year": 2000,
      "value": 0.6439999999999999
    },
    {
      "year": 2001,
      "value": 0.60795
    },
    {
      "year": 2002,
      "value": 0.4305
    },
    {
      "year": 2003,
      "value": 0.4894
    },
    {
      "year": 2004,
      "value": 0.4097
    },
    {
      "year": 2005,
      "value": 0.5054
    },
    {
      "year": 2006,
      "value": 0.8144
    },
    {
      "year": 2007,
      "value": 0.63435
    },
    {
      "year": 2008,
      "value": 0.5971
    },
    {
      "year": 2009,
      "value": 0.57685
    },
    {
      "year": 2010,
      "value": 0.414
    },
    {
      "year": 2011,
      "value": 0.5199
    },
    {
      "year": 2012,
      "value": 0.4172
    },
    {
      "year": 2013,
      "value": 0.4568
    },
    {
      "year": 2014,
      "value": 0.3505
    },
    {
      "year": 2015,
      "value": 0.4689
    },
    {
      "year": 2016,
      "value": 0.397
    },
    {
      "year": 2017,
      "value": 0.4939
    },
    {
      "year": 2018,
      "value": 0.4667
    },
    {
      "year": 2019,
      "value": 0.3838
    },
    {
      "year": 2020,
      "value": 0.4639
    },
    {
      "year": 2021,
      "value": 0.4304
    },
    {
      "year": 2022,
      "value": 0.4175
    },
    {
      "year": 2023,
      "value": 0.4633
    },
    {
      "year": 2024,
      "value": 0.4555
    }
  ],
  "enrollment_history_city": [
    {
      "year": 1996,
      "value": 1465.0
    },
    {
      "year": 1997,
      "value": 1437.0
    },
    {
      "year": 1998,
      "value": 1506.0
    },
    {
      "year": 1999,
      "value": 1433.0
    },
    {
      "year": 2001,
      "value": 1268.0
    },
    {
      "year": 2002,
      "value": 1371.0
    },
    {
      "year": 2003,
      "value": 1299.0
    },
    {
      "year": 2004,
      "value": 1221.0
    },
    {
      "year": 2005,
      "value": 1189.0
    },
    {
      "year": 2006,
      "value": 1442.0
    },
    {
      "year": 2007,
      "value": 1526.0
    },
    {
      "year": 2008,
      "value": 1452.0
    },
    {
      "year": 2009,
      "value": 1422.0
    },
    {
      "year": 2010,
      "value": 1460.0
    },
    {
      "year": 2011,
      "value": 1404.0
    },
    {
      "year": 2012,
      "value": 1329.0
    },
    {
      "year": 2013,
      "value": 1791.0
    },
    {
      "year": 2014,
      "value": 1919.0
    },
    {
      "year": 2015,
      "value": 2070.0
    },
    {
      "year": 2016,
      "value": 2064.0
    },
    {
      "year": 2017,
      "value": 2169.0
    },
    {
      "year": 2018,
      "value": 2178.0
    },
    {
      "year": 2019,
      "value": 2187.0
    },
    {
      "year": 2020,
      "value": 2339.0
    },
    {
      "year": 2021,
      "value": 2349.0
    },
    {
      "year": 2022,
      "value": 2559.0
    },
    {
      "year": 2023,
      "value": 2333.0
    },
    {
      "year": 2024,
      "value": 2506.0
    }
  ],
  "source": {
    "name": "College Scorecard + IPEDS HD",
    "vintage": "2025-05",
    "retrieved": "2026-05-08",
    "history_vintages": [
      1996,
      1997,
      1998,
      1999,
      2000,
      2001,
      2002,
      2003,
      2004,
      2005,
      2006,
      2007,
      2008,
      2009,
      2010,
      2011,
      2012,
      2013,
      2014,
      2015,
      2016,
      2017,
      2018,
      2019,
      2020,
      2021,
      2022,
      2023,
      2024
    ]
  }
}