{
  "state": "pr",
  "name": "Juana Diaz",
  "slug": "juana-diaz",
  "institution_count": 1,
  "institutions": [
    {
      "unitid": "404684",
      "slug": "emma-s-beauty-academy-juana-diaz-404684",
      "name": "Emma's Beauty Academy-Juana Diaz",
      "city": "Juana Diaz",
      "city_slug": "juana-diaz",
      "control": "private_forprofit",
      "pred_degree": "certificate",
      "earnings_median_5yr": null,
      "earnings_median_10yr": 17034,
      "earnings_progression": [
        {
          "year": 4,
          "value": null
        },
        {
          "year": 5,
          "value": null
        },
        {
          "year": 6,
          "value": 16502
        },
        {
          "year": 8,
          "value": 16726
        },
        {
          "year": 10,
          "value": 17034
        }
      ],
      "completion_rate_150": 0.6568,
      "completion_rate_history": [
        {
          "year": 1997,
          "value": 0.6234
        },
        {
          "year": 1999,
          "value": 0.8108
        },
        {
          "year": 2000,
          "value": 0.6849
        },
        {
          "year": 2001,
          "value": 0.5918
        },
        {
          "year": 2002,
          "value": 0.716
        },
        {
          "year": 2003,
          "value": 0.5448
        },
        {
          "year": 2004,
          "value": 0.673
        },
        {
          "year": 2005,
          "value": 0.486
        },
        {
          "year": 2006,
          "value": 0.5613
        },
        {
          "year": 2007,
          "value": 0.6483
        },
        {
          "year": 2008,
          "value": 0.6625
        },
        {
          "year": 2009,
          "value": 0.6184
        }
      ],
      "enrollment_undergrad": 318,
      "enrollment_history": [
        {
          "year": 1996,
          "value": 74.0
        },
        {
          "year": 1997,
          "value": 74.0
        },
        {
          "year": 1999,
          "value": 250.0
        },
        {
          "year": 2001,
          "value": 367.0
        },
        {
          "year": 2002,
          "value": 420.0
        },
        {
          "year": 2003,
          "value": 363.0
        },
        {
          "year": 2004,
          "value": 276.0
        },
        {
          "year": 2005,
          "value": 330.0
        },
        {
          "year": 2006,
          "value": 375.0
        },
        {
          "year": 2007,
          "value": 493.0
        },
        {
          "year": 2008,
          "value": 436.0
        },
        {
          "year": 2009,
          "value": 505.0
        }
      ],
      "median_debt": null,
      "default_rate": null,
      "tuition_in_state": null,
      "tuition_out_of_state": null,
      "long_arc": [
        {
          "metric": "enrollment_undergrad",
          "from_year": 1996,
          "to_year": 2009,
          "from_value": 74.0,
          "to_value": 505.0,
          "pct_change": 2.155,
          "direction": "rose"
        },
        {
          "metric": "earnings_median_10yr",
          "from_year": 2007,
          "to_year": 2020,
          "from_value": 12700.0,
          "to_value": 17034.0,
          "pct_change": 0.2889333333333333,
          "direction": "rose"
        },
        {
          "metric": "earnings_median_6yr",
          "from_year": 2005,
          "to_year": 2020,
          "from_value": 12900.0,
          "to_value": 16502.0,
          "pct_change": 0.24013333333333334,
          "direction": "rose"
        }
      ]
    }
  ],
  "earnings_median_city": 17034,
  "completion_rate_city": 0.6568,
  "completion_history_city": [
    {
      "year": 1997,
      "value": 0.6234
    },
    {
      "year": 1999,
      "value": 0.8108
    },
    {
      "year": 2000,
      "value": 0.6849
    },
    {
      "year": 2001,
      "value": 0.5918
    },
    {
      "year": 2002,
      "value": 0.716
    },
    {
      "year": 2003,
      "value": 0.5448
    },
    {
      "year": 2004,
      "value": 0.673
    },
    {
      "year": 2005,
      "value": 0.486
    },
    {
      "year": 2006,
      "value": 0.5613
    },
    {
      "year": 2007,
      "value": 0.6483
    },
    {
      "year": 2008,
      "value": 0.6625
    },
    {
      "year": 2009,
      "value": 0.6184
    }
  ],
  "enrollment_history_city": [
    {
      "year": 1996,
      "value": 74.0
    },
    {
      "year": 1997,
      "value": 74.0
    },
    {
      "year": 1999,
      "value": 250.0
    },
    {
      "year": 2001,
      "value": 367.0
    },
    {
      "year": 2002,
      "value": 420.0
    },
    {
      "year": 2003,
      "value": 363.0
    },
    {
      "year": 2004,
      "value": 276.0
    },
    {
      "year": 2005,
      "value": 330.0
    },
    {
      "year": 2006,
      "value": 375.0
    },
    {
      "year": 2007,
      "value": 493.0
    },
    {
      "year": 2008,
      "value": 436.0
    },
    {
      "year": 2009,
      "value": 505.0
    }
  ],
  "source": {
    "name": "College Scorecard + IPEDS HD",
    "vintage": "2025-05",
    "retrieved": "2026-05-08",
    "history_vintages": [
      1996,
      1997,
      1998,
      1999,
      2000,
      2001,
      2002,
      2003,
      2004,
      2005,
      2006,
      2007,
      2008,
      2009,
      2010,
      2011,
      2012,
      2013,
      2014,
      2015,
      2016,
      2017,
      2018,
      2019,
      2020,
      2021,
      2022,
      2023,
      2024
    ]
  }
}